switchbee/__init__.py
switchbee/const.py
switchbee/py.typed
switchbee/api/__init__.py
switchbee/api/utils.py
switchbee/central_unit/__init__.py
switchbee/device/__init__.py
aioswitchbee-0.1.0.dist-info/METADATA
aioswitchbee-0.1.0.dist-info/WHEEL
aioswitchbee-0.1.0.dist-info/top_level.txt
aioswitchbee-0.1.0.dist-info/RECORD
