Metadata-Version: 2.1
Name: aioswitchbee
Version: 0.1.0
Summary: WebSocket SwitchBee Python Integration.
Author-email: Jafar Atili <at.jafar@outlook.com>
Project-URL: homepage, https://pypi.org/project/pyswitchbee/
Project-URL: repository, https://github.com/jafar-atili/pySwitchbee/
Keywords: home,automation,switchbee,smart
Classifier: Intended Audience :: Developers
Classifier: Operating System :: OS Independent
Classifier: Topic :: Home Automation
Classifier: Topic :: Software Development :: Libraries :: Python Modules
Classifier: Typing :: Typed
Requires-Python: >=3.9
Requires-Dist: asyncio
Requires-Dist: aiohttp
